Metadata-Version: 2.1
Name: fastapienv
Version: 1.0.0
Summary: A Python module that creates a Python environment and generates FastAPI boilerplate code.
Home-page: UNKNOWN
Author: Gautam Sagar Mallela
Author-email: gautamsagar.mallela99@gmail.com
License: UNKNOWN
Keywords: python module fastapi boilerplate
Platform: UNKNOWN
